hybrid_search/__init__.py
hybrid_search/hybrid_pipeline.py
hybrid_search/hybrid_pipeline_config.py
fastembed_hybrid_pipeline-0.1.0.dist-info/METADATA
fastembed_hybrid_pipeline-0.1.0.dist-info/WHEEL
fastembed_hybrid_pipeline-0.1.0.dist-info/licenses/LICENSE
fastembed_hybrid_pipeline-0.1.0.dist-info/RECORD
