Metadata-Version: 2.4
Name: fastembed-hybrid-pipeline
Version: 0.1.0
Summary: Configurable Hybrid Search Pipeline with Qdrant and FastEmbed
Author-email: Brian O'Grady <genesysdatallc@gmail.com>
Maintainer-email: Brian O'Grady <genesysdatallc@gmail.com>
License: MIT License
License-File: LICENSE
Keywords: colbert,database,embeddings,late-interaction,qdrant,similarity-search,vector
Classifier: Development Status :: 4 - Beta
Classifier: Intended Audience :: Developers
Classifier: License :: OSI Approved :: MIT License
Classifier: Programming Language :: Python :: 3
Classifier: Programming Language :: Python :: 3.11
Classifier: Topic :: Database
Classifier: Topic :: Scientific/Engineering :: Artificial Intelligence
Classifier: Topic :: Software Development :: Libraries
Requires-Python: >=3.11
Requires-Dist: fastembed>=0.6.1
Requires-Dist: pydantic>=2.11.3
Requires-Dist: python-dotenv>=1.1.0
Requires-Dist: qdrant-client>=1.13.3
Provides-Extra: dev
Requires-Dist: build>=1.0.3; extra == 'dev'
Requires-Dist: mypy>=1.11.0; extra == 'dev'
Requires-Dist: pre-commit>=3.7.0; extra == 'dev'
Requires-Dist: pytest-asyncio>=0.23.0; extra == 'dev'
Requires-Dist: pytest-cov>=5.0.0; extra == 'dev'
Requires-Dist: pytest-mock>=3.14.0; extra == 'dev'
Requires-Dist: pytest-xdist>=3.6.0; extra == 'dev'
Requires-Dist: pytest>=8.2.0; extra == 'dev'
Requires-Dist: ruff<0.10,>=0.9.7; extra == 'dev'
Requires-Dist: twine>=4.0.2; extra == 'dev'
Provides-Extra: test
Requires-Dist: build>=1.0.3; extra == 'test'
Requires-Dist: mypy>=1.11.0; extra == 'test'
Requires-Dist: pre-commit>=3.7.0; extra == 'test'
Requires-Dist: pytest-asyncio>=0.23.0; extra == 'test'
Requires-Dist: pytest-cov>=5.0.0; extra == 'test'
Requires-Dist: pytest-mock>=3.14.0; extra == 'test'
Requires-Dist: pytest-xdist>=3.6.0; extra == 'test'
Requires-Dist: pytest>=8.2.0; extra == 'test'
Requires-Dist: ruff<0.10,>=0.9.7; extra == 'test'
Requires-Dist: twine>=4.0.2; extra == 'test'
